method_security/__init__.py
method_security/auth/__init__.py
method_security/auth/client.py
method_security/auth/raw_client.py
method_security/auth/types/__init__.py
method_security/auth/types/token_response.py
method_security/common/__init__.py
method_security/common/types/__init__.py
method_security/common/types/environment_id.py
method_security/core/__init__.py
method_security/core/api_error.py
method_security/core/client_wrapper.py
method_security/core/datetime_utils.py
method_security/core/file.py
method_security/core/force_multipart.py
method_security/core/http_client.py
method_security/core/http_response.py
method_security/core/http_sse/__init__.py
method_security/core/http_sse/_api.py
method_security/core/http_sse/_decoders.py
method_security/core/http_sse/_exceptions.py
method_security/core/http_sse/_models.py
method_security/core/jsonable_encoder.py
method_security/core/oauth_token_provider.py
method_security/core/pydantic_utilities.py
method_security/core/query_encoder.py
method_security/core/remove_none_from_dict.py
method_security/core/request_options.py
method_security/core/serialization.py
method_security/method_client.py
method_security/py.typed
method_security/v1/__init__.py
method_security/v1/audit/__init__.py
method_security/v1/audit/client.py
method_security/v1/audit/raw_client.py
method_security/v1/audit/types/__init__.py
method_security/v1/audit/types/action.py
method_security/v1/audit/types/actor.py
method_security/v1/audit/types/audit_event.py
method_security/v1/audit/types/audit_event_id.py
method_security/v1/audit/types/audit_events_response.py
method_security/v1/audit/types/audit_log_access.py
method_security/v1/audit/types/context.py
method_security/v1/audit/types/external_user_id.py
method_security/v1/audit/types/get_audit_events_request.py
method_security/v1/audit/types/group.py
method_security/v1/audit/types/group_id.py
method_security/v1/audit/types/ip_address.py
method_security/v1/audit/types/resource.py
methodsdk-0.0.18.dist-info/METADATA
methodsdk-0.0.18.dist-info/WHEEL
methodsdk-0.0.18.dist-info/RECORD
